withoutEnable/counter_4bit.v
module counter_4bit (
    input wire clk,
    input wire reset,
    output reg [3:0] count
);

always @(posedge clk or posedge reset) begin
    if (reset) begin
        count <=4'b0000;    // Reset counter to 0
    end else begin
        count <= count + 1; // Increment the counter
    end
end

endmodule

withoutEnable/counter_4bit_tb.v
module counter_4bit_tb;

reg clk;
reg reset;
wire [3:0] count;

// Instantiate the counter
counter_4bit uut (
    .clk(clk),
    .reset(reset),
    .count(count)
);

// Clock generation
always begin
    clk = 0;
    #5;        // Half period
    clk = 1;
    #5;        // Half period
end

initial begin
    // Initialize signals
    reset = 1;
    #10;       // Wait for clock cycles
    reset = 0; // Release reset

    // Run for a specific number of clock cycles
    repeat (20) @(posedge clk);

    // Finish simulation
    $finish;
end

initial begin
    // Monitor the count output
    // $timeformat(-9, 1, " ns", 8);
    $monitor("Time: %0d, count: %b", $time, count);
    $dumpfile("counter_4bit_tb.vcd");
    $dumpvars(0, counter_4bit_tb);
end


endmodule

counter_4bit_tb.vcd
$date
	Wed Oct 23 23:56:24 2024
$end
$version
	Icarus Verilog
$end
$timescale
	1s
$end
$scope module counter_4bit_tb $end
$var wire 4 ! count [3:0] $end
$var reg 1 " clk $end
$var reg 1 # reset $end
$scope module uut $end
$var wire 1 " clk $end
$var wire 1 # reset $end
$var reg 4 $ count [3:0] $end
$upscope $end
$upscope $end
$enddefinitions $end
#0
$dumpvars
b0 $
1#
0"
b0 !
$end
#5
1"
#10
0"
0#
#15
b1 !
b1 $
1"
#20
0"
#25
b10 !
b10 $
1"
#30
0"
#35
b11 !
b11 $
1"
#40
0"
#45
b100 !
b100 $
1"
#50
0"
#55
b101 !
b101 $
1"
#60
0"
#65
b110 !
b110 $
1"
#70
0"
#75
b111 !
b111 $
1"
#80
0"
#85
b1000 !
b1000 $
1"
#90
0"
#95
b1001 !
b1001 $
1"
#100
0"
#105
b1010 !
b1010 $
1"
#110
0"
#115
b1011 !
b1011 $
1"
#120
0"
#125
b1100 !
b1100 $
1"
#130
0"
#135
b1101 !
b1101 $
1"
#140
0"
#145
b1110 !
b1110 $
1"
#150
0"
#155
b1111 !
b1111 $
1"
#160
0"
#165
b0 !
b0 $
1"
#170
0"
#175
b1 !
b1 $
1"
#180
0"
#185
b10 !
b10 $
1"
#190
0"
#195
b11 !
b11 $
1"
#200
0"
#205
b100 !
b100 $
1"
