withEnable/counter_4bit_wEnable.v
module counter_4bit (
    input wire clk,
    input wire reset,
    input wire enable,
    output reg [3:0] count
);

always @(posedge clk or posedge reset) begin
    if (reset) begin
        count <=4'b0000;             // Reset counter to 0
    end
    else if (enable) begin
        count <= count + 1;         // Increment the counter
    end
end

endmodule

withEnable/counter_4bit_wEnable_tb.v
`timescale 1ns / 1ps

module counter_4bit_tb;

reg clk;
reg reset;
reg enable;
wire [3:0] count;

// Instantiate the counter
counter_4bit uut (
    .clk(clk),
    .reset(reset),
    .enable(enable),
    .count(count)
);

// Clock generation
always begin
    clk = 0;
    #5;                 // Half period
    clk = 1;
    #5;                 // Half period
end

// Test Sequence
initial begin
    // Initialize signals
    reset = 1;
    enable = 0;
    #10;                // Wait for clock cycles
    reset = 0;          // Release reset

    // Test counting with enable high
    enable = 1;         // Start counting
    #100 enable = 0;    // Stop counting after some time
    #20  reset = 1;     // Apply reset again
    #10  reset = 0;     // Release reset
    enable = 1;         // Start counting again to ensure the maximum value of the counter is 15

    #200 $stop;          // Stop simulation
end

initial begin
    // Monitor the count output
    $monitor("clk : %b, count: %b, reset: %b, enable = %b",clk, count, reset, enable);
    $dumpfile("counter_4bit_tb.vcd");
    $dumpvars(0, counter_4bit_tb);
end


endmodule

withEnable/counter_4bit_wEnable_tb.vcd
$date
	Sat Oct 26 12:33:57 2024
$end
$version
	Icarus Verilog
$end
$timescale
	1ps
$end
$scope module counter_4bit_tb $end
$var wire 4 ! count [3:0] $end
$var reg 1 " clk $end
$var reg 1 # enable $end
$var reg 1 $ reset $end
$scope module uut $end
$var wire 1 " clk $end
$var wire 1 # enable $end
$var wire 1 $ reset $end
$var reg 4 % count [3:0] $end
$upscope $end
$upscope $end
$enddefinitions $end
#0
$dumpvars
b0 %
1$
0#
0"
b0 !
$end
#5000
1"
#10000
0"
1#
0$
#15000
b1 !
b1 %
1"
#20000
0"
#25000
b10 !
b10 %
1"
#30000
0"
#35000
b11 !
b11 %
1"
#40000
0"
#45000
b100 !
b100 %
1"
#50000
0"
#55000
b101 !
b101 %
1"
#60000
0"
#65000
b110 !
b110 %
1"
#70000
0"
#75000
b111 !
b111 %
1"
#80000
0"
#85000
b1000 !
b1000 %
1"
#90000
0"
#95000
b1001 !
b1001 %
1"
#100000
0"
#105000
b1010 !
b1010 %
1"
#110000
0"
0#
#115000
1"
#120000
0"
#125000
1"
#130000
b0 !
b0 %
0"
1$
#135000
1"
#140000
0"
1#
0$
#145000
b1 !
b1 %
1"
#150000
0"
#155000
b10 !
b10 %
1"
#160000
0"
#165000
b11 !
b11 %
1"
#170000
0"
#175000
b100 !
b100 %
1"
#180000
0"
#185000
b101 !
b101 %
1"
#190000
0"
#195000
b110 !
b110 %
1"
#200000
0"
#205000
b111 !
b111 %
1"
#210000
0"
#215000
b1000 !
b1000 %
1"
#220000
0"
#225000
b1001 !
b1001 %
1"
#230000
0"
#235000
b1010 !
b1010 %
1"
#240000
0"
#245000
b1011 !
b1011 %
1"
#250000
0"
#255000
b1100 !
b1100 %
1"
#260000
0"
#265000
b1101 !
b1101 %
1"
#270000
0"
#275000
b1110 !
b1110 %
1"
#280000
0"
#285000
b1111 !
b1111 %
1"
#290000
0"
#295000
b0 !
b0 %
1"
#300000
0"
#305000
b1 !
b1 %
1"
#310000
0"
#315000
b10 !
b10 %
1"
#320000
0"
#325000
b11 !
b11 %
1"
#330000
0"
#335000
b100 !
b100 %
1"
